djinfo/__init__.py
djinfo/__version__
djinfo/admin.py
djinfo/apps.py
djinfo/decorators.py
djinfo/models.py
djinfo/settings.py
djinfo/urls.py
djinfo/utils.py
djinfo/views.py
djinfo/migrations/__init__.py
djinfo/runtests/__init__.py
djinfo/runtests/runtests.py
djinfo/runtests/settings.py
djinfo/runtests/urls.py
djinfo/static/djinfo/.sass-cache/a2b8d2122a6b45762e047e714f2d00b357bc4e66/djinfo.scssc
djinfo/static/djinfo/css/djinfo.css
djinfo/static/djinfo/css/djinfo.css.map
djinfo/static/djinfo/img/logo-django.svg
djinfo/static/djinfo/sass/djinfo.scss
djinfo/templates/djinfo/env.inc.html
djinfo/templates/djinfo/index.html
djinfo/templates/djinfo/setting-value.inc.html
djinfo/templates/djinfo/setting.inc.html
djinfo/templatetags/__init__.py
djinfo/templatetags/djinfo_tags.py
djinfo/tests/__init__.py
djinfo/tests/test_settings.py
djinfo/tests/test_views.py
djinfo-0.0.6.dist-info/LICENSE
djinfo-0.0.6.dist-info/METADATA
djinfo-0.0.6.dist-info/WHEEL
djinfo-0.0.6.dist-info/top_level.txt
djinfo-0.0.6.dist-info/zip-safe
djinfo-0.0.6.dist-info/RECORD
